Metadata-Version: 2.1
Name: bbcu.bt-flor
Version: 1.0.26
Summary: BT-FLOR - Build Transcripts From LOng-Reads
Home-page: UNKNOWN
Author: Refael Kohen
Author-email: refael.kohen@gmail.com, refael.kohen@weizmann.ac.il
License: UNKNOWN
Platform: UNKNOWN
